tifeatures/__init__.py
tifeatures/db.py
tifeatures/dbmodel.py
tifeatures/dependencies.py
tifeatures/errors.py
tifeatures/factory.py
tifeatures/layer.py
tifeatures/main.py
tifeatures/middleware.py
tifeatures/model.py
tifeatures/settings.py
tifeatures/filter/__init__.py
tifeatures/filter/evaluate.py
tifeatures/filter/filters.py
tifeatures/resources/__init__.py
tifeatures/resources/enums.py
tifeatures/resources/response.py
tifeatures/templates/collection.html
tifeatures/templates/collections.html
tifeatures/templates/conformance.html
tifeatures/templates/debug.html
tifeatures/templates/footer.html
tifeatures/templates/header.html
tifeatures/templates/item.html
tifeatures/templates/items.html
tifeatures/templates/landing.html
tifeatures/templates/queryables.html
tifeatures-0.1.0a4.dist-info/METADATA
tifeatures-0.1.0a4.dist-info/WHEEL
tifeatures-0.1.0a4.dist-info/licenses/LICENSE
tifeatures-0.1.0a4.dist-info/RECORD
