Metadata-Version: 2.1
Name: tifeatures
Version: 0.1.0a4
Summary: Simple and Fast Geospatial Features API for PostGIS.
Project-URL: Homepage, https://developmentseed.org/tifeatures
Project-URL: Source, https://github.com/developmentseed/tifeatures
Project-URL: Documentation, https://developmentseed.org/tifeatures/
Author-email: Vincent Sarago <vincent@developmentseed.org>, David Bitner <david@developmentseed.org>
License: MIT License
License-File: LICENSE
Keywords: FastAPI,OGC Features,POSTGIS
Classifier: Intended Audience :: Information Technology
Classifier: Intended Audience :: Science/Research
Classifier: License :: OSI Approved :: BSD License
Classifier: Programming Language :: Python :: 3.8
Classifier: Programming Language :: Python :: 3.9
Classifier: Programming Language :: Python :: 3.10
Classifier: Programming Language :: Python :: 3.11
Classifier: Topic :: Scientific/Engineering :: GIS
Requires-Python: >=3.8
Requires-Dist: asyncpg>=0.23.0
Requires-Dist: buildpg>=0.3
Requires-Dist: ciso8601~=2.2.0
Requires-Dist: fastapi>=0.87
Requires-Dist: geojson-pydantic>=0.4.3
Requires-Dist: importlib-resources>=1.1.0; python_version < '3.9'
Requires-Dist: jinja2<4.0.0,>=2.11.2
Requires-Dist: orjson
Requires-Dist: pygeofilter<0.3.0,>=0.2.0
Requires-Dist: starlette-cramjam<0.4,>=0.3
Requires-Dist: typing-extensions; python_version < '3.9.2'
Provides-Extra: dev
Requires-Dist: pre-commit; extra == 'dev'
Provides-Extra: docs
Requires-Dist: mkdocs; extra == 'docs'
Requires-Dist: mkdocs-material; extra == 'docs'
Requires-Dist: pdocs; extra == 'docs'
Requires-Dist: pygments; extra == 'docs'
Provides-Extra: server
Requires-Dist: uvicorn[standard]<0.19.0,>=0.12.0; extra == 'server'
Provides-Extra: test
Requires-Dist: httpx; extra == 'test'
Requires-Dist: psycopg2; extra == 'test'
Requires-Dist: pytest; extra == 'test'
Requires-Dist: pytest-asyncio; extra == 'test'
Requires-Dist: pytest-benchmark; extra == 'test'
Requires-Dist: pytest-cov; extra == 'test'
Requires-Dist: pytest-pgsql; extra == 'test'
Requires-Dist: sqlalchemy<1.4,>=1.1; extra == 'test'
